{
  "passes": [
    {
      "name": "skannamu:glitch_program",
      "vertex": "glitch_effect_v",
      "fragment": "glitch_effect_f",

      "intarget": "minecraft:main",
      "outtarget": "minecraft:main",

      "samplers": [
        { "name": "Sampler0", "id": "minecraft:main" }
      ],
      "uniforms": [
        {
          "name": "Time",
          "type": "float",
          "value": 0.0,
          "auto": "time"
        },
        {
          "name": "ScreenSize",
          "type": "vec2",
          "value": [0.0, 0.0],
          "auto": "screen_size"
        }
      ],
      "blend": {
        "func": "add",
        "srcrgb": "one",
        "dstrgb": "zero"
      },
      "addshadow": false
    }
  ]
}